{
	"info": {
		"_postman_id": "5739c7f9-2945-4543-91f9-5ab886e3b9ed",
		"name": "collection2",
		"schema": "https://schema.getpostman.com/json/collection/v2.1.0/collection.json",
		"_exporter_id": "24920830"
	},
	"item": [
		{
			"name": "https://jsonplaceholder.typicode.com/users",
			"request": {
				"method": "GET",
				"header": [],
				"url": {
					"raw": "https://jsonplaceholder.typicode.com/users",
					"protocol": "https",
					"host": [
						"jsonplaceholder",
						"typicode",
						"com"
					],
					"path": [
						"users"
					]
				}
			},
			"response": []
		}
	]
}
